spheropy/__init__.py
spheropy/spheropy.py
SpheroPy-0.0.4.dist-info/LICENSE
SpheroPy-0.0.4.dist-info/METADATA
SpheroPy-0.0.4.dist-info/WHEEL
SpheroPy-0.0.4.dist-info/top_level.txt
SpheroPy-0.0.4.dist-info/RECORD
