Metadata-Version: 2.1
Name: SpheroPy
Version: 0.0.4
Summary: Control Sphero devices.
Home-page: https://github.com/irvinec/SpheroPy
Author: Casey Irvine
Author-email: caseyi@outlook.com
License: LICENSE
Platform: UNKNOWN
Provides-Extra: pybluez
Requires-Dist: pybluez ; extra == 'pybluez'
Provides-Extra: pygatt
Requires-Dist: pygatt ; extra == 'pygatt'
Provides-Extra: winble
Requires-Dist: winble ; extra == 'winble'
